urless/__init__.py
urless/urless.py
urless-2.4.dist-info/METADATA
urless-2.4.dist-info/WHEEL
urless-2.4.dist-info/entry_points.txt
urless-2.4.dist-info/top_level.txt
urless-2.4.dist-info/RECORD
