Metadata-Version: 2.1
Name: urless
Version: 2.4
Summary: De-clutter a list of URLs
Home-page: https://github.com/xnl-h4ck3r/urless
Author: @xnl-h4ck3r
Requires-Dist: argparse
Requires-Dist: pyyaml
Requires-Dist: termcolor
Requires-Dist: urlparse3
Requires-Dist: chardet
Requires-Dist: requests
